[
  {
    "name": "热门商圈地点1",
    "value": 333,
    "latitude": "39.989449",
    "longitude": "116.481565"
  },
  {
    "name": "热门商圈地点2",
    "value": 333,
    "latitude": "39.989934",
    "longitude": "116.484401"
  },
  {
    "name": "银闸二十号院2",
    "value": 31233,
    "latitude": "39.2989934",
    "longitude": "115.484401"
  },
  {
    "name": "银闸二十号院3",
    "value": 33433,
    "latitude": "39.489934",
    "longitude": "116.424401"
  },
  {
    "name": "银闸二十号院4",
    "value": 33763,
    "latitude": "39.959934",
    "longitude": "116.1484401"
  },
  {
    "name": "银闸二十号院6",
    "value": 24333,
    "latitude": "39.989934",
    "longitude": "116.1484401"
  }
]